lab2/hamming7_4_encode.sv
//
// lab2 : version 06/12/2020
// 
`timescale 1ns / 1ps
module hamming7_4_encode(
	output logic [7:1] e,
	input logic [4:1] d
	);

	logic p1,p2,p3;

	assign p1 = d[1] ^ d[2] ^ d[4];
	assign p2 = d[1] ^ d[3] ^ d[4];
	assign p3 = d[2] ^ d[3] ^ d[4];

	assign e = {d[4], d[3], d[2], p3, d[1], p2, p1};

endmodule

lab2/tb_hamming7_4_encode.sv
`timescale 1ns / 1ps
module tb_hamming7_4_encode ();	// this is the top level testbench wrapper

	// ----- fill in the number of rows, inputs and outputs in the text file -----
	parameter ROWS=16, INPUTS=4, OUTPUTS=7;
	logic [INPUTS- 1:0] data_in;
	logic [OUTPUTS-1:0] expected_out;
	logic [OUTPUTS-1:0] sim_out;	// signal containing the simulated output;
	logic [INPUTS+OUTPUTS-1:0] test_vectors [0:ROWS-1];
	integer i;	// variable for loop index
	integer mm_count;	// variable to hold the mismatch count

	// instantiate the unit under test
	hamming7_4_encode uut (.e(sim_out[6:0]), .d(data_in[3:0]));



	initial begin
		$dumpfile("tb_hamming7_4_encode.vcd");
		$dumpvars();

		mm_count = 0;   // zero mismatch count

 		// read all of the test vectors from a file into
		// array: test_vectors
		$readmemb("tb_hamming7_4_encode.txt", test_vectors);

		for (i=0; i<ROWS; i=i+1) begin
			// read each vector (row) into the input data and
			// expected output variables – at this time the
			// data_in is applied to the unit under test
			{data_in, expected_out} = test_vectors [i];

			#10;    // artificial wait 10 ns for inputs to settle
			// now compare the output from uut to expected value
			if (sim_out !== expected_out) begin
				// display mismatch
				$display("Mismatch--loop index i: %d; input: %b, expected: %b, received: %b",
					i, data_in, expected_out, sim_out);

				mm_count = mm_count + 1;        // increment mismatch count

			end	// end of if
			#10;    // add 10 ns for symmetry
		end	// end of for loop

		// tell designer we're done with the simulation
		if (mm_count == 0) begin
			$display("Simulation complete - no mismatches!!!");
		end else begin
			$display("Simulation complete - %d mismatches!!!",
				mm_count);
		end
		$finish;
	end	// end of initial block

endmodule

lab2/tb_hamming7_4_encode.vcd
$date
	Sun Apr 10 21:17:01 2022
$end
$version
	ModelSim Version 2020.1
$end
$timescale
	1ps
$end

$scope module tb_hamming7_4_encode $end
$var parameter 32 ! ROWS $end
$var parameter 32 " INPUTS $end
$var parameter 32 # OUTPUTS $end
$var reg 4 $ data_in [3:0] $end
$var reg 7 % expected_out [6:0] $end
$var reg 7 & sim_out [6:0] $end
$var integer 32 ' i $end
$var integer 32 ( mm_count $end

$scope module uut $end
$var reg 7 ) e [7:1] $end
$var wire 1 * d [4] $end
$var wire 1 + d [3] $end
$var wire 1 , d [2] $end
$var wire 1 - d [1] $end
$var reg 1 . p1 $end
$var reg 1 / p2 $end
$var reg 1 0 p3 $end
$upscope $end
$upscope $end

$scope begin std $end
$upscope $end
$enddefinitions $end
#0
$dumpvars
b0 $
b0 %
b0 &
b0 )
0.
0/
00
b10000 !
b100 "
b111 #
b0 '
b0 (
0-
0,
0+
0*
$end
#20000
b1 '
b111 %
b1 $
1-
1.
1/
b111 )
b111 &
#40000
b10 '
b11001 %
b10 $
0-
1,
10
0/
b11001 )
b11001 &
#60000
b11 '
b11110 %
b11 $
1-
0.
1/
b11110 )
b11110 &
#80000
b100 '
b101010 %
b100 $
0-
0,
1+
b101010 )
b101010 &
#100000
b101 '
b101101 %
b101 $
1-
1.
0/
b101101 )
b101101 &
#120000
b110 '
b110011 %
b110 $
0-
1,
00
1/
b110011 )
b110011 &
#140000
b111 '
b110100 %
b111 $
1-
0.
0/
b110100 )
b110100 &
#160000
b1000 '
b1001011 %
b1000 $
0-
0,
0+
1*
10
1.
1/
b1001011 )
b1001011 &
#180000
b1001 '
b1001100 %
b1001 $
1-
0.
0/
b1001100 )
b1001100 &
#200000
b1010 '
b1010010 %
b1010 $
0-
1,
00
1/
b1010010 )
b1010010 &
#220000
b1011 '
b1010101 %
b1011 $
1-
1.
0/
b1010101 )
b1010101 &
#240000
b1100 '
b1100001 %
b1100 $
0-
0,
1+
b1100001 )
b1100001 &
#260000
b1101 '
b1100110 %
b1101 $
1-
0.
1/
b1100110 )
b1100110 &
#280000
b1110 '
b1111000 %
b1110 $
0-
1,
10
0/
b1111000 )
b1111000 &
#300000
b1111 '
b1111111 %
b1111 $
1-
1.
1/
b1111111 )
b1111111 &
#320000
b10000 '
